{"blog.md":"3_8CoXcg","blog_announcing-vite2.md":"CfHXCY0t","blog_announcing-vite3.md":"CjKIE9ji","blog_announcing-vite4-3.md":"BcP-hMgZ","blog_announcing-vite4.md":"BjIsDHrg","blog_announcing-vite5-1.md":"CIoVXwAD","blog_announcing-vite5.md":"Cwr09KIp","blog_announcing-vite6.md":"CX95L3Ob","blog_announcing-vite7.md":"CsNpw2TS","changes_hotupdate-hook.md":"5vwH4dGA","changes_index.md":"BsvyLfuo","changes_per-environment-apis.md":"BkWAL6ot","changes_shared-plugins-during-build.md":"Bs2-QAxX","changes_ssr-using-modulerunner.md":"B_6SHg2w","changes_this-environment-in-hooks.md":"DJ34zAxq","config_build-options.md":"C-5P20T8","config_dep-optimization-options.md":"CeiCThMe","config_index.md":"CzxlF0LT","config_preview-options.md":"Cfxxb4bB","config_server-options.md":"DAl0SmMd","config_shared-options.md":"CZyWRM19","config_ssr-options.md":"CXUq0G9j","config_worker-options.md":"BTHRQPsX","guide_api-environment-frameworks.md":"BvkvKP1z","guide_api-environment-instances.md":"Bi8tlBF4","guide_api-environment-plugins.md":"DzGnjZrE","guide_api-environment-runtimes.md":"DDHwJFWn","guide_api-environment.md":"Cpqa2V6T","guide_api-hmr.md":"CdI3EBjm","guide_api-javascript.md":"EQGfycpp","guide_api-plugin.md":"qtCYO0yG","guide_api-vite-runtime.md":"BC0xb3CQ","guide_assets.md":"DwssTkyy","guide_backend-integration.md":"DJ7XzbWW","guide_build.md":"B7kardMP","guide_cli.md":"BLsZ0qxF","guide_comparisons.md":"Buur8X_c","guide_dep-pre-bundling.md":"1dFD6FID","guide_env-and-mode.md":"CpwFSNuK","guide_features.md":"CxiAFRUJ","guide_index.md":"dTNGNRSY","guide_migration-from-v1.md":"BE0abuBn","guide_migration-from-v2.md":"Dg0KCdnO","guide_migration-from-v3.md":"BPJbt1JQ","guide_migration-from-v4.md":"Cf8VOhXi","guide_migration-from-v5.md":"Bz8m0VbX","guide_migration.md":"YCb7zyFl","guide_performance.md":"CRRrCJID","guide_philosophy.md":"DpiL9ba9","guide_rolldown.md":"Cs4gARHC","guide_ssr.md":"ZcHm84IS","guide_static-deploy.md":"DFklzFU9","guide_troubleshooting.md":"DAFRqQRh","guide_using-plugins.md":"fKzaDCpL","guide_why.md":"nSUOys80","index.md":"OUsRP2ae","plugins_index.md":"BLbN1Q5w","readme.md":"LCEIkOeo","releases.md":"DyBt1UaP","team.md":"BRusUd8v"}
